{
  "userInfo":{
    "userName":"admin",
    "userIcon":"../../static/user.png",
    "music": {
      "id": 0,
      "name": "粤语残片",
      "singer": "陈奕迅",
      "img": "https://y.gtimg.cn/music/photo_new/T002R150x150M000003nMzes28P7wv.jpg?max_age=2592000",
      "url": "http://ws.stream.qqmusic.qq.com/1249555.m4a?fromtag=46",
      "lyric": ""
    }
  },
  "musicList":[
    {
      "name":"夜的第七章",
      "bgImg":"https://y.gtimg.cn/music/photo_new/T002R150x150M000002jLGWe16Tf1H.jpg?max_age=2592000",
      "list":[
        {
          "id": 466722,
          "name":"夜的第七章",
          "singer":"周杰伦",
          "img":"https://y.gtimg.cn/music/photo_new/T002R150x150M000002jLGWe16Tf1H.jpg?max_age=2592000",
          "url":"http://ws.stream.qqmusic.qq.com/466722.m4a?fromtag=46",
          "lyric":""
        },
        {
          "id":102066257,
          "name":"听妈妈的话",
          "singer":"周杰伦",
          "img":"https://y.gtimg.cn/music/photo_new/T002R150x150M000002jLGWe16Tf1H.jpg?max_age=2592000",
          "url":"http://ws.stream.qqmusic.qq.com/102066257.m4a?fromtag=46",
          "lyric":""
        },
        {
          "id":102698215,
          "name":"千里之外",
          "singer":"周杰伦",
          "img":"https://y.gtimg.cn/music/photo_new/T002R150x150M000002jLGWe16Tf1H.jpg?max_age=2592000",
          "url":"http://ws.stream.qqmusic.qq.com/102698215.m4a?fromtag=46",
          "lyric":""
        },
        {
          "id":102066448,
          "name":"本草纲目",
          "singer":"周杰伦",
          "img":"https://y.gtimg.cn/music/photo_new/T002R150x150M000002jLGWe16Tf1H.jpg?max_age=2592000",
          "url":"http://ws.stream.qqmusic.qq.com/102066448.m4a?fromtag=46",
          "lyric":""
        },
        {
          "id":102066449,
          "name":"退后",
          "singer":"周杰伦",
          "img":"https://y.gtimg.cn/music/photo_new/T002R150x150M000002jLGWe16Tf1H.jpg?max_age=2592000",
          "url":"http://ws.stream.qqmusic.qq.com/102066449.m4a?fromtag=46",
          "lyric":""
        },
        {
          "id":101101739,
          "name":"红模仿",
          "singer":"周杰伦",
          "img":"https://y.gtimg.cn/music/photo_new/T002R150x150M000002jLGWe16Tf1H.jpg?max_age=2592000",
          "url":"http://ws.stream.qqmusic.qq.com/101101739.m4a?fromtag=46",
          "lyric":""
        },
        {
          "id":7179645,
          "name":"心雨",
          "singer":"周杰伦",
          "img":"https://y.gtimg.cn/music/photo_new/T002R150x150M000002jLGWe16Tf1H.jpg?max_age=2592000",
          "url":"http://ws.stream.qqmusic.qq.com/7179645.m4a?fromtag=46",
          "lyric":""
        },
        {
          "id":102320103,
          "name":"白色风车",
          "singer":"周杰伦",
          "img":"https://y.gtimg.cn/music/photo_new/T002R150x150M000002jLGWe16Tf1H.jpg?max_age=2592000",
          "url":"http://ws.stream.qqmusic.qq.com/102320103.m4a?fromtag=46",
          "lyric":""
        },
        {
          "id":102320104,
          "name":"迷迭香",
          "singer":"周杰伦",
          "img":"https://y.gtimg.cn/music/photo_new/T002R150x150M000002jLGWe16Tf1H.jpg?max_age=2592000",
          "url":"http://ws.stream.qqmusic.qq.com/102320104.m4a?fromtag=46",
          "lyric":""
        },
        {
          "id":102320104,
          "name":"迷迭香",
          "singer":"周杰伦",
          "img":"https://y.gtimg.cn/music/photo_new/T002R150x150M000002jLGWe16Tf1H.jpg?max_age=2592000",
          "url":"http://ws.stream.qqmusic.qq.com/102320104.m4a?fromtag=46",
          "lyric":""
        }
    ]},
    {
      "name":"十一月的肖邦",
      "bgImg":"https://y.gtimg.cn/music/photo_new/T002R150x150M0000024bjiL2aocxT.jpg?max_age=2592000",
      "list":[
        {
          "id":718477,
          "name":"夜曲",
          "singer":"周杰伦",
          "img":"https://y.gtimg.cn/music/photo_new/T002R150x150M0000024bjiL2aocxT.jpg?max_age=2592000",
          "url":"http://ws.stream.qqmusic.qq.com/718477.m4a?fromtag=46",
          "lyric":""
        },
        {
          "id":718481,
          "name":"蓝色风暴",
          "singer":"周杰伦",
          "img":"https://y.gtimg.cn/music/photo_new/T002R150x150M0000024bjiL2aocxT.jpg?max_age=2592000",
          "url":"http://ws.stream.qqmusic.qq.com/718481.m4a?fromtag=46",
          "lyric":""
        },
        {
          "id":718475,
          "name":"发如雪",
          "singer":"周杰伦",
          "img":"https://y.gtimg.cn/music/photo_new/T002R150x150M0000024bjiL2aocxT.jpg?max_age=2592000",
          "url":"http://ws.stream.qqmusic.qq.com/718475.m4a?fromtag=46",
          "lyric":""
        },
        {
          "id":718480,
          "name":"黑色毛衣",
          "singer":"周杰伦",
          "img":"https://y.gtimg.cn/music/photo_new/T002R150x150M0000024bjiL2aocxT.jpg?max_age=2592000",
          "url":"http://ws.stream.qqmusic.qq.com/718480.m4a?fromtag=46",
          "lyric":""
        },
        {
          "id":718476,
          "name":"四面楚歌",
          "singer":"周杰伦",
          "img":"https://y.gtimg.cn/music/photo_new/T002R150x150M0000024bjiL2aocxT.jpg?max_age=2592000",
          "url":"http://ws.stream.qqmusic.qq.com/718476.m4a?fromtag=46",
          "lyric":""
        },
        {
          "id":718479,
          "name":"枫",
          "singer":"周杰伦",
          "img":"https://y.gtimg.cn/music/photo_new/T002R150x150M0000024bjiL2aocxT.jpg?max_age=2592000",
          "url":"http://ws.stream.qqmusic.qq.com/718479.m4a?fromtag=46",
          "lyric":""
        },
        {
          "id":718482,
          "name":"浪漫手机",
          "singer":"周杰伦",
          "img":"https://y.gtimg.cn/music/photo_new/T002R150x150M0000024bjiL2aocxT.jpg?max_age=2592000",
          "url":"http://ws.stream.qqmusic.qq.com/718482.m4a?fromtag=46",
          "lyric":""
        },
        {
          "id":718484,
          "name":"逆鳞",
          "singer":"周杰伦",
          "img":"https://y.gtimg.cn/music/photo_new/T002R150x150M0000024bjiL2aocxT.jpg?max_age=2592000",
          "url":"http://ws.stream.qqmusic.qq.com/718484.m4a?fromtag=46",
          "lyric":""
        },
        {
          "id":718483,
          "name":"麦芽糖",
          "singer":"周杰伦",
          "img":"https://y.gtimg.cn/music/photo_new/T002R150x150M0000024bjiL2aocxT.jpg?max_age=2592000",
          "url":"http://ws.stream.qqmusic.qq.com/718483.m4a?fromtag=46",
          "lyric":""
        },
        {
          "id":718486,
          "name":"珊瑚海",
          "singer":"周杰伦",
          "img":"https://y.gtimg.cn/music/photo_new/T002R150x150M0000024bjiL2aocxT.jpg?max_age=2592000",
          "url":"http://ws.stream.qqmusic.qq.com/718486.m4a?fromtag=46",
          "lyric":""
        },
        {
          "id":162360,
          "name":"飘移",
          "singer":"周杰伦",
          "img":"https://y.gtimg.cn/music/photo_new/T002R150x150M000000ibLEm3rEG2S.jpg?max_age=2592000",
          "url":"http://ws.stream.qqmusic.qq.com/162360.m4a?fromtag=46",
          "lyric":""
        },
        {
          "id":5105986,
          "name":"一路向北",
          "singer":"周杰伦",
          "img":"https://y.gtimg.cn/music/photo_new/T002R150x150M000002MAeob3zLXwZ.jpg?max_age=2592000",
          "url":"http://ws.stream.qqmusic.qq.com/5105986.m4a?fromtag=46",
          "lyric":""
        }
    ]},
    {
      "name":"如果你也喜欢陈奕迅",
      "bgImg":"https://y.gtimg.cn/music/photo_new/T002R150x150M0000002yffm37Ajv0.jpg?max_age=2592000",
      "list":[
        {
          "id":1760030,
          "name":"完(粤语)",
          "singer":"陈奕迅",
          "img":"https://y.gtimg.cn/music/photo_new/T002R150x150M000000v3GsC2xEmcx.jpg?max_age=2592000",
          "url":"http://ws.stream.qqmusic.qq.com/1760030.m4a?fromtag=46",
          "lyric":""
        },
        {
          "id":1249550,
          "name":"富士山下",
          "singer":"陈奕迅",
          "img":"https://y.gtimg.cn/music/photo_new/T002R150x150M000003nMzes28P7wv.jpg?max_age=2592000",
          "url":"http://ws.stream.qqmusic.qq.com/1249550.m4a?fromtag=46",
          "lyric":""
        },
        {
          "id":1249555,
          "name":"粤语残片",
          "singer":"陈奕迅",
          "img":"https://y.gtimg.cn/music/photo_new/T002R150x150M000003nMzes28P7wv.jpg?max_age=2592000",
          "url":"http://ws.stream.qqmusic.qq.com/1249555.m4a?fromtag=46",
          "lyric":""
        },
        {
          "id":107800143,
          "name":"歌颂(Live)",
          "singer":"陈奕迅",
          "img":"https://y.gtimg.cn/music/photo_new/T002R150x150M0000002yffm37Ajv0.jpg?max_age=2592000",
          "url":"http://ws.stream.qqmusic.qq.com/107800143.m4a?fromtag=46",
          "lyric":""
        },
        {
          "id":1410008,
          "name":"最冷一天",
          "singer":"陈奕迅",
          "img":"https://y.gtimg.cn/music/photo_new/T002R150x150M000001ZLjzB19w316.jpg?max_age=2592000",
          "url":"http://ws.stream.qqmusic.qq.com/1410008.m4a?fromtag=46",
          "lyric":""
        },
        {
          "id":104775916,
          "name":"陪你度过漫长岁月(国语)",
          "singer":"陈奕迅",
          "img":"https://y.gtimg.cn/music/photo_new/T002R150x150M000002DAg4x3jVzHI.jpg?max_age=2592000",
          "url":"http://ws.stream.qqmusic.qq.com/104775916.m4a?fromtag=46",
          "lyric":""
        },
        {
          "id":1021078,
          "name":"孤独患者",
          "singer":"陈奕迅",
          "img":"https://y.gtimg.cn/music/photo_new/T002R150x150M000003YQ8lP3NBXKl.jpg?max_age=2592000",
          "url":"http://ws.stream.qqmusic.qq.com/1021078.m4a?fromtag=46",
          "lyric":""
        },
        {
          "id":1313990,
          "name":"红玫瑰",
          "singer":"陈奕迅",
          "img":"https://y.gtimg.cn/music/photo_new/T002R150x150M000003yQidc3s7P65.jpg?max_age=2592000",
          "url":"http://ws.stream.qqmusic.qq.com/1313990.m4a?fromtag=46",
          "lyric":""
        },
        {
          "id":1251166,
          "name":"浮夸",
          "singer":"陈奕迅",
          "img":"https://y.gtimg.cn/music/photo_new/T002R150x150M000003J6fvc0bVJon.jpg?max_age=2592000",
          "url":"http://ws.stream.qqmusic.qq.com/1251166.m4a?fromtag=46",
          "lyric":""
        },
        {
          "id":1249546,
          "name":"裙下之臣",
          "singer":"陈奕迅",
          "img":"https://y.gtimg.cn/music/photo_new/T002R150x150M000003nMzes28P7wv.jpg?max_age=2592000",
          "url":"http://ws.stream.qqmusic.qq.com/1249546.m4a?fromtag=46",
          "lyric":""
        },
        {
          "id":1313993,
          "name":"好久不见",
          "singer":"陈奕迅",
          "img":"https://y.gtimg.cn/music/photo_new/T002R150x150M000003yQidc3s7P65.jpg?max_age=2592000",
          "url":"http://ws.stream.qqmusic.qq.com/1313993.m4a?fromtag=46",
          "lyric":""
        },
        {
          "id":1313988,
          "name":"淘汰",
          "singer":"陈奕迅",
          "img":"https://y.gtimg.cn/music/photo_new/T002R150x150M000003yQidc3s7P65.jpg?max_age=2592000",
          "url":"http://ws.stream.qqmusic.qq.com/1313988.m4a?fromtag=46",
          "lyric":""
        },
        {
          "id":1843621,
          "name":"一丝不挂",
          "singer":"陈奕迅",
          "img":"https://y.gtimg.cn/music/photo_new/T002R150x150M000001sjRhH0wqa4Q.jpg?max_age=2592000",
          "url":"http://ws.stream.qqmusic.qq.com/1843621.m4a?fromtag=46",
          "lyric":""
        },
        {
          "id":1250812,
          "name":"苦瓜",
          "singer":"陈奕迅",
          "img":"https://y.gtimg.cn/music/photo_new/T002R150x150M000000Iv0BM0vOHkK.jpg?max_age=2592000",
          "url":"http://ws.stream.qqmusic.qq.com/1250812.m4a?fromtag=46",
          "lyric":""
        },
        {
          "id":1760029,
          "name":"信任",
          "singer":"陈奕迅",
          "img":"https://y.gtimg.cn/music/photo_new/T002R150x150M000000v3GsC2xEmcx.jpg?max_age=2592000",
          "url":"http://ws.stream.qqmusic.qq.com/1760029.m4a?fromtag=46",
          "lyric":""
        }
    ]}
  ]
}
